setup.py
ADA_sdk.egg-info/PKG-INFO
ADA_sdk.egg-info/SOURCES.txt
ADA_sdk.egg-info/dependency_links.txt
ADA_sdk.egg-info/requires.txt
ADA_sdk.egg-info/top_level.txt
ada/__init__.py
ada/base.py
ada/listener.py
ada/config/__init__.py
ada/config/api_config.py
ada/features/__init__.py
ada/features/execution.py
ada/features/testcase.py
ada/features/upload_image.py
ada/utils/APIException.py
ada/utils/__init__.py