Metadata-Version: 1.0
Name: ADA-sdk
Version: 2.8
Summary: Python SDK for Automation data analytics API
Home-page: UNKNOWN
Author: UNKNOWN
Author-email: UNKNOWN
License: UNKNOWN
Platform: UNKNOWN
